{
  "lastUpdated": "2026-02-16T05:00:00.865Z",
  "totalEvents": 3,
  "odds": [
    {
      "eventId": "539495",
      "sport": "Baseball",
      "homeTeam": "Baltimore Orioles",
      "awayTeam": "Kansas City Royals",
      "startTime": "2014-10-10",
      "bookmakers": [
        {
          "name": "Bet365",
          "homeOdds": 1.83,
          "awayOdds": 2.67,
          "timestamp": "2026-02-16T05:00:00.864Z"
        },
        {
          "name": "William Hill",
          "homeOdds": 2.94,
          "awayOdds": 1.74,
          "timestamp": "2026-02-16T05:00:00.864Z"
        },
        {
          "name": "Pinnacle",
          "homeOdds": 1.96,
          "awayOdds": 2.41,
          "timestamp": "2026-02-16T05:00:00.864Z"
        }
      ],
      "lastUpdated": "2026-02-16T05:00:00.864Z",
      "source": "manual"
    },
    {
      "eventId": "539495",
      "sport": "Baseball",
      "homeTeam": "Baltimore Orioles",
      "awayTeam": "Kansas City Royals",
      "startTime": "2014-10-10",
      "bookmakers": [
        {
          "name": "Bet365",
          "homeOdds": 2.41,
          "awayOdds": 1.95,
          "timestamp": "2026-02-16T05:00:00.864Z"
        },
        {
          "name": "William Hill",
          "homeOdds": 1.44,
          "awayOdds": 3.92,
          "timestamp": "2026-02-16T05:00:00.864Z"
        },
        {
          "name": "Pinnacle",
          "homeOdds": 3.7,
          "awayOdds": 1.5,
          "timestamp": "2026-02-16T05:00:00.864Z"
        }
      ],
      "lastUpdated": "2026-02-16T05:00:00.864Z",
      "source": "manual"
    },
    {
      "eventId": "1168911",
      "sport": "American Football",
      "homeTeam": "Stanford",
      "awayTeam": "Washington State",
      "startTime": "2014-10-10",
      "bookmakers": [
        {
          "name": "Bet365",
          "homeOdds": 1.37,
          "awayOdds": 5.36,
          "timestamp": "2026-02-16T05:00:00.864Z",
          "overUnder": [
            {
              "total": 2.5,
              "over": 1.8768508523271117,
              "under": 1.9835238225892051
            }
          ]
        },
        {
          "name": "William Hill",
          "homeOdds": 2.82,
          "awayOdds": 1.67,
          "timestamp": "2026-02-16T05:00:00.864Z",
          "overUnder": [
            {
              "total": 2.5,
              "over": 2.09027777315407,
              "under": 1.9242744789604318
            }
          ]
        },
        {
          "name": "Pinnacle",
          "homeOdds": 3.51,
          "awayOdds": 1.58,
          "timestamp": "2026-02-16T05:00:00.864Z",
          "overUnder": [
            {
              "total": 2.5,
              "over": 1.9999726622681022,
              "under": 1.8732372161117699
            }
          ]
        }
      ],
      "lastUpdated": "2026-02-16T05:00:00.864Z",
      "source": "manual"
    }
  ]
}